microns_utils/__init__.py
microns_utils/adapter_utils.py
microns_utils/ap_utils.py
microns_utils/cluster_utils.py
microns_utils/config_utils.py
microns_utils/datajoint_utils.py
microns_utils/datetime_utils.py
microns_utils/errors.py
microns_utils/filepath_utils.py
microns_utils/mesh_utils.py
microns_utils/misc_utils.py
microns_utils/model_utils.py
microns_utils/ng_utils.py
microns_utils/plot_utils.py
microns_utils/transform_utils.py
microns_utils/version.py
microns_utils/version_utils.py
microns_utils/widget_utils.py
microns_utils-0.1.10.dist-info/LICENSE
microns_utils-0.1.10.dist-info/METADATA
microns_utils-0.1.10.dist-info/WHEEL
microns_utils-0.1.10.dist-info/top_level.txt
microns_utils-0.1.10.dist-info/RECORD
